loadotenv/__init__.py
loadotenv/main.py
loadotenv-1.0.0.dist-info/LICENSE
loadotenv-1.0.0.dist-info/METADATA
loadotenv-1.0.0.dist-info/WHEEL
loadotenv-1.0.0.dist-info/top_level.txt
loadotenv-1.0.0.dist-info/RECORD
